CoderElijah/E.py
CoderElijah/__init__.py
CoderElijah/rickPy.py
coderelijah-0.3.7.dist-info/LICENSE
coderelijah-0.3.7.dist-info/WHEEL
coderelijah-0.3.7.dist-info/METADATA
coderelijah-0.3.7.dist-info/RECORD
